{
  "_id":{"$oid":"000000000000000000000001"},
  "beginLat":36.1667,
  "beginLng":-86.7833,
  "endLat":36.1699,
  "endLng":-115.1398,
  "tripName":"Las Vegas",
  "cash":1000,
  "origin":"Nashville, TN, USA",
  "destination":"Las Vegas, NV, USA",
  "startDate":"2014-08-25",
  "endDate":"2014-08-30",
  "mpg":35,
  "carPhoto":"img/gold.jpg",
  "photos":[]
}

{
  "_id":{"$oid":"000000000000000000000002"},
  "beginLat":36.1667,
  "beginLng":-86.7833,
  "endLat":36.1699,
  "endLng":-115.1398,
  "tripName":"Las Vegas",
  "cash":2000,
  "origin":"Nashville, TN, USA",
  "destination":"Las Vegas, NV, USA",
  "startDate":"2014-08-25",
  "endDate":"2014-08-30",
  "mpg":37,
  "carPhoto":"img/gold.jpg",
  "photos":[]
}

{
  "_id":{"$oid":"000000000000000000000003"},
  "beginLat":36.1667,
  "beginLng":-86.7833,
  "endLat":36.1699,
  "endLng":-115.1398,
  "tripName":"Las Vegas",
  "cash":3000,
  "origin":"Nashville, TN, USA",
  "destination":"Las Vegas, NV, USA",
  "startDate":"2014-08-25",
  "endDate":"2014-08-30",
  "mpg":40,
  "carPhoto":"img/gold.jpg",
  "photos":[]
}
